{
  "_class": "group",
  "booleanOperation": -1,
  "clippingMaskMode": 0,
  "do_objectID": "B3364DBC-E899-4175-BA20-806BBCBAE316",
  "exportOptions": {
    "_class": "exportOptions",
    "do_objectID": "A660EC00-48D9-4375-9462-2ABB08B8695A",
    "exportFormats": [
    ],
    "includedLayerIds": [
    ],
    "layerOptions": 0,
    "shouldTrim": false
  },
  "frame": {
    "_class": "rect",
    "constrainProportions": false,
    "do_objectID": "12E8D143-744D-45E4-B89E-55E2039FA7DE",
    "height": 501,
    "width": 800.9999999999999,
    "x": 0.5,
    "y": 19.5
  },
  "groupLayout": {
    "_class": "MSImmutableFreeformGroupLayout",
    "do_objectID": "63DA17EE-1091-4726-B361-1401999644DB"
  },
  "hasClickThrough": false,
  "hasClippingMask": false,
  "isFixedToViewport": false,
  "isFlippedHorizontal": false,
  "isFlippedVertical": false,
  "isLocked": false,
  "isVisible": true,
  "layerListExpandedType": 2,
  "layers": [
    {
      "class": "group",
      "id": "1CF3A034-9BE6-4B6E-BEEC-6CA404F09623"
    },
    {
      "class": "group",
      "id": "6611CEAA-C841-483B-94C5-5343F2869C03"
    }
  ],
  "name": "Group",
  "nameIsFixed": false,
  "resizingConstraint": 63,
  "resizingType": 0,
  "rotation": 0,
  "shouldBreakMaskChain": false,
  "style": {
    "_class": "style",
    "do_objectID": "EBE67CD2-947E-4023-A7BD-7A8CBCF8ABAE",
    "endMarkerType": 0,
    "fills": [
      {
        "_class": "fill",
        "color": {
          "_class": "color",
          "alpha": 1,
          "blue": 0,
          "green": 0,
          "red": 0
        },
        "fillType": 0,
        "isEnabled": true,
        "noiseIndex": 0,
        "noiseIntensity": 0,
        "patternFillType": 1,
        "patternTileScale": 1
      }
    ],
    "miterLimit": 10,
    "startMarkerType": 0,
    "windingRule": 1
  }
}