{
  "_class": "text",
  "attributedString": {
    "_class": "attributedString",
    "attributes": [
      {
        "_class": "stringAttribute",
        "attributes": {
          "MSAttributedStringFontAttribute": {
            "_class": "fontDescriptor",
            "attributes": {
              "name": "Helvetica",
              "size": 24
            }
          },
          "ligature": 0
        },
        "length": 2,
        "location": 0
      }
    ],
    "string": "10"
  },
  "automaticallyDrawOnUnderlyingPath": false,
  "booleanOperation": -1,
  "clippingMaskMode": 0,
  "do_objectID": "5CC33A19-F38A-4A15-B9FB-ED0F52367CD4",
  "dontSynchroniseWithSymbol": false,
  "exportOptions": {
    "_class": "exportOptions",
    "do_objectID": "D8A01664-FADC-456B-A9EA-BA098D9A221A",
    "exportFormats": [
    ],
    "includedLayerIds": [
    ],
    "layerOptions": 0,
    "shouldTrim": false
  },
  "frame": {
    "_class": "rect",
    "constrainProportions": false,
    "do_objectID": "7D12F85D-BAF7-4559-9C01-DDB98C4369D9",
    "height": 29,
    "width": 27,
    "x": 267.6,
    "y": 527.0000000000006
  },
  "glyphBounds": "{{2, 6}, {24, 18}}",
  "hasClippingMask": false,
  "isFixedToViewport": false,
  "isFlippedHorizontal": false,
  "isFlippedVertical": false,
  "isLocked": false,
  "isVisible": true,
  "layerListExpandedType": 0,
  "lineSpacingBehaviour": 1,
  "name": "10",
  "nameIsFixed": false,
  "resizingConstraint": 47,
  "resizingType": 0,
  "rotation": 0,
  "shouldBreakMaskChain": false,
  "style": {
    "_class": "style",
    "blur": {
      "_class": "blur",
      "center": "{0.5, 0.5}",
      "do_objectID": "A396D12D-ECB3-4F2E-B3FD-0B62E2796BF7",
      "isEnabled": false,
      "motionAngle": 0,
      "radius": 16,
      "saturation": 1,
      "type": 0
    },
    "do_objectID": "4693480F-3E2E-44CE-AD75-0FA5D509D50E",
    "endMarkerType": 0,
    "fills": [
      {
        "_class": "fill",
        "color": {
          "_class": "color",
          "alpha": 1,
          "blue": 0,
          "green": 0,
          "red": 0
        },
        "fillType": 0,
        "isEnabled": true,
        "noiseIndex": 0,
        "noiseIntensity": 0,
        "patternFillType": 1,
        "patternTileScale": 1
      }
    ],
    "miterLimit": 10,
    "startMarkerType": 0,
    "textStyle": {
      "_class": "textStyle",
      "do_objectID": "1075CBF3-3F68-4C69-928C-E1D92AE2CA9F",
      "encodedAttributes": {
        "MSAttributedStringFontAttribute": {
          "_class": "fontDescriptor",
          "attributes": {
            "name": "Helvetica",
            "size": 24
          }
        },
        "ligature": 0
      },
      "verticalAlignment": 0
    },
    "windingRule": 1
  },
  "textBehaviour": 0
}