{
  "_class": "group",
  "booleanOperation": -1,
  "clippingMaskMode": 0,
  "do_objectID": "58022106-EFFC-4358-8C40-D324F7762F44",
  "exportOptions": {
    "_class": "exportOptions",
    "exportFormats": [
    ],
    "includedLayerIds": [
    ],
    "layerOptions": 0,
    "shouldTrim": false
  },
  "frame": {
    "_class": "rect",
    "constrainProportions": false,
    "height": 46.13073541998681,
    "width": 27.67844125199201,
    "x": 237.6825825459357,
    "y": 309.6292817319771
  },
  "groupLayout": {
    "_class": "MSImmutableFreeformGroupLayout"
  },
  "hasClickThrough": false,
  "hasClippingMask": false,
  "isFixedToViewport": false,
  "isFlippedHorizontal": false,
  "isFlippedVertical": false,
  "isLocked": false,
  "isVisible": true,
  "layerListExpandedType": 0,
  "layers": [
    {
      "class": "rectangle",
      "id": "D58FBF82-DB30-408F-9437-FFC5D5483245"
    },
    {
      "class": "shapePath",
      "id": "EBF4CB4F-7809-438B-A080-39EE1285E494"
    },
    {
      "class": "shapePath",
      "id": "928184C9-A148-4126-A51A-9972531EE616"
    },
    {
      "class": "oval",
      "id": "4197846B-15F0-4318-8CD8-B7733E79BC32"
    }
  ],
  "name": "Group",
  "nameIsFixed": false,
  "resizingConstraint": 63,
  "resizingType": 0,
  "rotation": 0,
  "shouldBreakMaskChain": false,
  "style": {
    "_class": "style",
    "blur": {
      "_class": "blur",
      "center": "{0.5, 0.5}",
      "isEnabled": false,
      "motionAngle": 0,
      "radius": 4.05,
      "saturation": 1,
      "type": 0
    },
    "endMarkerType": 0,
    "miterLimit": 10,
    "startMarkerType": 0,
    "windingRule": 1
  }
}