{
  "_class": "bitmap",
  "booleanOperation": -1,
  "clippingMask": "{{0, 0}, {1, 1}}",
  "clippingMaskMode": 0,
  "do_objectID": "0BCD376E-2B7E-4F7B-9ECA-EBF7F6FE3249",
  "exportOptions": {
    "_class": "exportOptions",
    "exportFormats": [
    ],
    "includedLayerIds": [
    ],
    "layerOptions": 0,
    "shouldTrim": false
  },
  "fillReplacesImage": false,
  "frame": {
    "_class": "rect",
    "constrainProportions": true,
    "height": 899,
    "width": 1323,
    "x": 4207,
    "y": 169
  },
  "hasClippingMask": false,
  "image": {
    "_class": "MSJSONFileReference",
    "_ref": "images/140b7d07006378b00165726bbe94c87dd184577a.png",
    "_ref_class": "MSImageData"
  },
  "intendedDPI": 144,
  "isFixedToViewport": false,
  "isFlippedHorizontal": false,
  "isFlippedVertical": false,
  "isLocked": false,
  "isVisible": true,
  "layerListExpandedType": 0,
  "name": "Bitmap",
  "nameIsFixed": false,
  "resizingConstraint": 63,
  "resizingType": 0,
  "rotation": 0,
  "shouldBreakMaskChain": false,
  "style": {
    "_class": "style",
    "endMarkerType": 0,
    "miterLimit": 10,
    "startMarkerType": 0,
    "windingRule": 1
  }
}