{
  "_class": "group",
  "booleanOperation": -1,
  "clippingMaskMode": 0,
  "do_objectID": "AEC07E6E-9B65-4601-A6E0-694DE6861F0F",
  "exportOptions": {
    "_class": "exportOptions",
    "do_objectID": "FBD1BDE0-C23C-4B99-A169-FE16D09D57AE",
    "exportFormats": [
    ],
    "includedLayerIds": [
    ],
    "layerOptions": 0,
    "shouldTrim": false
  },
  "frame": {
    "_class": "rect",
    "constrainProportions": false,
    "do_objectID": "24F2AC6E-6E6B-4F79-BB6F-37CDBFC38FD4",
    "height": 501,
    "width": 800.9999999999999,
    "x": 0.5,
    "y": 19.5
  },
  "groupLayout": {
    "_class": "MSImmutableFreeformGroupLayout",
    "do_objectID": "302ED5E2-E6F1-456E-8C31-68F18505CE53"
  },
  "hasClickThrough": false,
  "hasClippingMask": false,
  "isFixedToViewport": false,
  "isFlippedHorizontal": false,
  "isFlippedVertical": false,
  "isLocked": false,
  "isVisible": true,
  "layerListExpandedType": 2,
  "layers": [
    {
      "class": "group",
      "id": "00FDBE64-8579-4EE9-A2C3-EA16573C14AC"
    },
    {
      "class": "group",
      "id": "1CF1A701-32DD-4236-9A07-D58B2C71896E"
    }
  ],
  "name": "Group",
  "nameIsFixed": false,
  "resizingConstraint": 63,
  "resizingType": 0,
  "rotation": 0,
  "shouldBreakMaskChain": false,
  "style": {
    "_class": "style",
    "do_objectID": "CE12A30F-F089-46B8-9192-CB864EAD8290",
    "endMarkerType": 0,
    "fills": [
      {
        "_class": "fill",
        "color": {
          "_class": "color",
          "alpha": 1,
          "blue": 0,
          "green": 0,
          "red": 0
        },
        "fillType": 0,
        "isEnabled": true,
        "noiseIndex": 0,
        "noiseIntensity": 0,
        "patternFillType": 1,
        "patternTileScale": 1
      }
    ],
    "miterLimit": 10,
    "startMarkerType": 0,
    "windingRule": 1
  }
}