{
  "_class": "text",
  "attributedString": {
    "_class": "attributedString",
    "attributes": [
      {
        "_class": "stringAttribute",
        "attributes": {
          "MSAttributedStringFontAttribute": {
            "_class": "fontDescriptor",
            "attributes": {
              "name": "DINNextLTPro-Regular",
              "size": 12
            }
          },
          "ligature": 0
        },
        "length": 3,
        "location": 0
      }
    ],
    "string": "200"
  },
  "automaticallyDrawOnUnderlyingPath": false,
  "booleanOperation": -1,
  "clippingMaskMode": 0,
  "do_objectID": "ED1859C6-EBFD-4153-8EF9-E500B2C1F54C",
  "dontSynchroniseWithSymbol": false,
  "exportOptions": {
    "_class": "exportOptions",
    "do_objectID": "90EBE2E3-3648-4702-AA3B-BFB297D254C8",
    "exportFormats": [
    ],
    "includedLayerIds": [
    ],
    "layerOptions": 0,
    "shouldTrim": false
  },
  "frame": {
    "_class": "rect",
    "constrainProportions": false,
    "do_objectID": "187C1F19-395A-40E9-ACC5-E8B96B735684",
    "height": 15,
    "width": 20,
    "x": 324.8333333333334,
    "y": 0
  },
  "glyphBounds": "{{0, 0}, {19, 10}}",
  "hasClippingMask": false,
  "isFixedToViewport": false,
  "isFlippedHorizontal": false,
  "isFlippedVertical": false,
  "isLocked": false,
  "isVisible": true,
  "layerListExpandedType": 0,
  "lineSpacingBehaviour": 1,
  "name": "200",
  "nameIsFixed": false,
  "resizingConstraint": 47,
  "resizingType": 0,
  "rotation": 0,
  "shouldBreakMaskChain": false,
  "style": {
    "_class": "style",
    "do_objectID": "16506D28-826F-49C9-AF6E-39F4F2DD08F8",
    "endMarkerType": 0,
    "fills": [
      {
        "_class": "fill",
        "color": {
          "_class": "color",
          "alpha": 1,
          "blue": 0,
          "green": 0,
          "red": 0
        },
        "fillType": 0,
        "isEnabled": true,
        "noiseIndex": 0,
        "noiseIntensity": 0,
        "patternFillType": 1,
        "patternTileScale": 1
      }
    ],
    "miterLimit": 10,
    "startMarkerType": 0,
    "textStyle": {
      "_class": "textStyle",
      "do_objectID": "517C067A-AB56-47AE-A86E-A90A11685059",
      "encodedAttributes": {
        "MSAttributedStringFontAttribute": {
          "_class": "fontDescriptor",
          "attributes": {
            "name": "DINNextLTPro-Regular",
            "size": 12
          }
        },
        "ligature": 0
      },
      "verticalAlignment": 0
    },
    "windingRule": 1
  },
  "textBehaviour": 0
}