{
  "_class": "shapePath",
  "booleanOperation": -1,
  "clippingMaskMode": 0,
  "do_objectID": "9FA27052-4B3C-4125-82AF-2215AF75EFFB",
  "edited": true,
  "exportOptions": {
    "_class": "exportOptions",
    "do_objectID": "4890DFF6-B75C-4E99-A27F-40527A4269A2",
    "exportFormats": [
    ],
    "includedLayerIds": [
    ],
    "layerOptions": 0,
    "shouldTrim": false
  },
  "frame": {
    "_class": "rect",
    "constrainProportions": false,
    "do_objectID": "9F700C22-9016-42F5-B7C8-02A0DDC8A49B",
    "height": 4.999999999999997,
    "width": 0.9999999999999996,
    "x": 350.4999999999999,
    "y": 0
  },
  "hasClippingMask": false,
  "isClosed": false,
  "isFixedToViewport": false,
  "isFlippedHorizontal": false,
  "isFlippedVertical": false,
  "isLocked": false,
  "isVisible": true,
  "layerListExpandedType": 0,
  "name": "Path",
  "nameIsFixed": false,
  "pointRadiusBehaviour": 1,
  "points": [
    {
      "_class": "curvePoint",
      "cornerRadius": 0,
      "curveFrom": "{0.5, 0}",
      "curveMode": 1,
      "curveTo": "{0.5, 0}",
      "hasCurveFrom": false,
      "hasCurveTo": false,
      "point": "{0.5, 0}"
    },
    {
      "_class": "curvePoint",
      "cornerRadius": 0,
      "curveFrom": "{0.5, 1}",
      "curveMode": 1,
      "curveTo": "{0.5, 1}",
      "hasCurveFrom": false,
      "hasCurveTo": false,
      "point": "{0.5, 1}"
    }
  ],
  "resizingConstraint": 63,
  "resizingType": 0,
  "rotation": 0,
  "shouldBreakMaskChain": false,
  "style": {
    "_class": "style",
    "borders": [
      {
        "_class": "border",
        "color": {
          "_class": "color",
          "alpha": 1,
          "blue": 0.5333333333333333,
          "green": 0.5333333333333333,
          "red": 0.5333333333333333
        },
        "fillType": 0,
        "isEnabled": true,
        "position": 0,
        "thickness": 1
      }
    ],
    "do_objectID": "E643A18A-1445-4FC3-9B9A-BFF67F3E624B",
    "endMarkerType": 0,
    "miterLimit": 10,
    "startMarkerType": 0,
    "windingRule": 1
  }
}