{
  "_class": "shapePath",
  "booleanOperation": -1,
  "clippingMaskMode": 0,
  "do_objectID": "A57A4034-2F8D-4CD7-AFF6-35E2B1128511",
  "edited": true,
  "exportOptions": {
    "_class": "exportOptions",
    "do_objectID": "C9372792-23AC-4429-9B36-5CA01DD2F780",
    "exportFormats": [
    ],
    "includedLayerIds": [
    ],
    "layerOptions": 0,
    "shouldTrim": false
  },
  "frame": {
    "_class": "rect",
    "constrainProportions": false,
    "do_objectID": "AAD4D43D-EAFE-497E-B79B-6EE30BF6BD07",
    "height": 233,
    "width": 2,
    "x": 2991,
    "y": 702
  },
  "hasClippingMask": false,
  "isClosed": false,
  "isFixedToViewport": false,
  "isFlippedHorizontal": false,
  "isFlippedVertical": false,
  "isLocked": false,
  "isVisible": true,
  "layerListExpandedType": 0,
  "name": "Line",
  "nameIsFixed": false,
  "pointRadiusBehaviour": 1,
  "points": [
    {
      "_class": "curvePoint",
      "cornerRadius": 0,
      "curveFrom": "{0.74999999999999856, 0.0016334635833707}",
      "curveMode": 1,
      "curveTo": "{0.74999999999999856, 0.0016334635833707}",
      "hasCurveFrom": false,
      "hasCurveTo": false,
      "point": "{0.74999999999999856, 0.0016334635833707}"
    },
    {
      "_class": "curvePoint",
      "cornerRadius": 0,
      "curveFrom": "{0.74999999999999856, 0.0016334635833707}",
      "curveMode": 1,
      "curveTo": "{0.74999999999999856, 0.0016334635833707}",
      "hasCurveFrom": false,
      "hasCurveTo": false,
      "point": "{0.75, 1}"
    }
  ],
  "resizingConstraint": 63,
  "resizingType": 0,
  "rotation": 0,
  "shouldBreakMaskChain": false,
  "style": {
    "_class": "style",
    "borderOptions": {
      "_class": "borderOptions",
      "dashPattern": [
      ],
      "do_objectID": "50899508-AA39-47C3-803F-76F86474B326",
      "isEnabled": false,
      "lineCapStyle": 2,
      "lineJoinStyle": 0
    },
    "borders": [
      {
        "_class": "border",
        "color": {
          "_class": "color",
          "alpha": 1,
          "blue": 0,
          "green": 0,
          "red": 0
        },
        "fillType": 0,
        "isEnabled": true,
        "position": 0,
        "thickness": 3
      }
    ],
    "do_objectID": "668D82C1-25BC-4455-8A3B-7756B5A13EF4",
    "endDecorationType": 0,
    "endMarkerType": 0,
    "fills": [
      {
        "_class": "fill",
        "color": {
          "_class": "color",
          "alpha": 1,
          "blue": 0.847,
          "green": 0.847,
          "red": 0.847
        },
        "fillType": 0,
        "isEnabled": false,
        "noiseIndex": 0,
        "noiseIntensity": 0,
        "patternFillType": 1,
        "patternTileScale": 1
      }
    ],
    "miterLimit": 10,
    "shadows": [
      {
        "_class": "shadow",
        "blurRadius": 4,
        "color": {
          "_class": "color",
          "alpha": 0.5,
          "blue": 0,
          "green": 0,
          "red": 0
        },
        "contextSettings": {
          "_class": "graphicsContextSettings",
          "blendMode": 0,
          "opacity": 1
        },
        "isEnabled": false,
        "offsetX": 0,
        "offsetY": 2,
        "spread": 0
      }
    ],
    "startMarkerType": 4,
    "windingRule": 1
  }
}